Metadata-Version: 2.4
Name: hello-world-example-luongtdt
Version: 0.1.0
Summary: A simple Hello World Python package
Author-email: Luong Tran <tamluong.td@gmail.com>
License: MIT
Requires-Python: >=3.7
License-File: LICENSE
Dynamic: license-file
